azure_recommendations/__init__.py
azure_recommendations/recommendation/__init__.py
azure_recommendations/recommendation/advisor_recommendations.py
azure_recommendations/recommendation/get_vm_price.py
azure_recommendations/recommendation/network_recommendations.py
azure_recommendations/recommendation/utils.py
azure_recommendations/recommendation/vm_recommendations.py
azure_recommendations/recommendation/vm_resize_recommendations.py
azure_recommendations-0.4.4.dist-info/LICENCE
azure_recommendations-0.4.4.dist-info/METADATA
azure_recommendations-0.4.4.dist-info/WHEEL
azure_recommendations-0.4.4.dist-info/top_level.txt
azure_recommendations-0.4.4.dist-info/RECORD
