Metadata-Version: 2.1
Name: azure_recommendations
Version: 0.4.4
Summary: Provides Azure recommendations
Author-email: "dheeraj.banodha" <dheeraj.banodha@impetus.com>
Classifier: Programming Language :: Python :: 3
Classifier: Operating System :: OS Independent
Requires-Python: >=3.7
License-File: LICENCE
Requires-Dist: azure-mgmt-network >=1.12.0
Requires-Dist: azure-mgmt-advisor
Requires-Dist: azure-mgmt-resource
Requires-Dist: azure-mgmt-compute
Requires-Dist: azure-mgmt-common
Requires-Dist: azure-mgmt-subscription
Requires-Dist: azure-identity
Requires-Dist: azure-mgmt-monitor
